{
    "data": [
        {
            "id": 1,
            " title": "this is an example",
            "type": "Ecommerce",
            "name": "Apple",
            "title":"Restaurant Landing Page",
            "image": "https://static-cse.canva.com/blob/951427/1600w-CrM91Tjbmbc.jpg",
            "source": "https://fancy-tiramisu-211459.netlify.app/index.html"
        },
        {
            "id": 2,
            "type": "Business",
            "name": "Banana",
            "image": "https://static-cse.canva.com/blob/951427/1600w-CrM91Tjbmbc.jpg",
            "source": "https://fancy-tiramisu-211459.netlify.app/index.html"
        },
        {
            "id": 3,
            "type": "WebApp",
            "name": "HAHA",
            "image": "https://static-cse.canva.com/blob/951427/1600w-CrM91Tjbmbc.jpg",
            "source": "https://fancy-tiramisu-211459.netlify.app/index.html"
        },
        {
            "id": 4,
            "type": "WebApp",
            "name": "HAHA",
            "image": "https://static-cse.canva.com/blob/951427/1600w-CrM91Tjbmbc.jpg",
            "source": "https://fancy-tiramisu-211459.netlify.app/index.html"
        },
        {
            "id": 5,
            "type": "WebApp",
            "name": "HAHA",
            "image": "https://static-cse.canva.com/blob/951427/1600w-CrM91Tjbmbc.jpg",
            "source": "https://fancy-tiramisu-211459.netlify.app/index.html"
        },
        {
            "id": 6,
            "type": "WebApp",
            "name": "HAHA",
            "image": "https://static-cse.canva.com/blob/951427/1600w-CrM91Tjbmbc.jpg",
            "source": "https://fancy-tiramisu-211459.netlify.app/index.html"
        },
        {
            "id": 7,
            "type": "WebApp",
            "name": "HAHA",
            "image": "https://static-cse.canva.com/blob/951427/1600w-CrM91Tjbmbc.jpg",
            "source": "https://fancy-tiramisu-211459.netlify.app/index.html"
        },
        {
            "id": 8,
            "type": "WebApp",
            "name": "HAHA",
            "image": "https://static-cse.canva.com/blob/951427/1600w-CrM91Tjbmbc.jpg",
            "source": "https://fancy-tiramisu-211459.netlify.app/index.html"
        },
        {
            "id": 9,
            "type": "WebApp",
            "name": "HAHA",
            "image": "https://static-cse.canva.com/blob/951427/1600w-CrM91Tjbmbc.jpg",
            "source": "https://fancy-tiramisu-211459.netlify.app/index.html"
        },
        {
            "id": 10,
            "type": "WebApp",
            "name": "HAHA",
            "image": "https://static-cse.canva.com/blob/951427/1600w-CrM91Tjbmbc.jpg",
            "source": "https://fancy-tiramisu-211459.netlify.app/index.html"
        },
        {
            "id": 11,
            "type": "WebApp",
            "name": "HAHA",
            "image": "https://static-cse.canva.com/blob/951427/1600w-CrM91Tjbmbc.jpg",
            "source": "https://fancy-tiramisu-211459.netlify.app/index.html"
        },
        {
            "id": 12,
            "type": "WebApp",
            "name": "HAHA",
            "image": "https://static-cse.canva.com/blob/951427/1600w-CrM91Tjbmbc.jpg",
            "source": "https://fancy-tiramisu-211459.netlify.app/index.html"
        }
        
    ]
}